rindle/__init__.py
rindle/rindle.cpython-39-darwin.so
rindle-0.1.1.dist-info/METADATA
rindle-0.1.1.dist-info/WHEEL
rindle-0.1.1.dist-info/RECORD
