Metadata-Version: 2.2
Name: rindle
Version: 0.1.1
Summary: Dataset preparation library with Python bindings for sliding window tensors
Keywords: time series,windowing,sliding window,dataset builder,feature engineering,ML,forecasting,finance,quant,trading,stocks,normalization,scaling,numpy,pandas
Author-Email: Eric Gilerson <ericgilerson@gmail.com>
Classifier: Development Status :: 3 - Alpha
Classifier: Programming Language :: Python
Classifier: Programming Language :: Python :: 3
Classifier: Programming Language :: C++
Classifier: License :: Other/Proprietary License
Classifier: Operating System :: OS Independent
Project-URL: Homepage, https://github.com/EricGilerson/rindle
Project-URL: Repository, https://github.com/EricGilerson/rindle
Project-URL: Issues, https://github.com/EricGilerson/rindle/issues
Requires-Python: >=3.9
Requires-Dist: numpy>=1.23
Provides-Extra: dev
Requires-Dist: scikit-build-core>=0.5; extra == "dev"
Requires-Dist: build; extra == "dev"
